utilfunction/__init__.py
utilfunction/astyper.py
utilfunction/bib2md.py
utilfunction/handle_json.py
utilfunction/path_finder.py
utilfunction/pq.py
utilfunction-1.0.2.dist-info/LICENSE
utilfunction-1.0.2.dist-info/METADATA
utilfunction-1.0.2.dist-info/WHEEL
utilfunction-1.0.2.dist-info/top_level.txt
utilfunction-1.0.2.dist-info/RECORD
