Metadata-Version: 2.1
Name: utilfunction
Version: 1.0.2
Summary: The Python package utilfunction wraps and distributes useful functions in an easy-to-use way.
Home-page: https://github.com/DSDanielPark/utilfunction
Author: parkminwoo
Author-email: parkminwoo1991@gmail.com
Keywords: Utils,Utility,Preprocessing,Analysis
Classifier: Development Status :: 3 - Alpha
Classifier: Intended Audience :: Developers
Classifier: Natural Language :: English
Classifier: Programming Language :: Python
Classifier: Programming Language :: Python :: 3.6
Classifier: Programming Language :: Python :: 3.7
Classifier: Programming Language :: Python :: 3.8
Classifier: Programming Language :: Python :: 3.9
Classifier: Programming Language :: Python :: Implementation :: CPython
Requires-Python: >=3.6
License-File: LICENSE
Requires-Dist: pandas
Requires-Dist: numpy
Requires-Dist: pybtex
